{
  "timestamp": "2025-08-01T05:35:51.165395",
  "value_metrics": {
    "timestamp": "2025-08-01T05:35:51.164670",
    "period": "all_time",
    "execution_summary": {
      "total_executions": 1,
      "successful_executions": 0,
      "failed_executions": 1,
      "success_rate": 0.0,
      "total_effort_hours": 2,
      "avg_effort": 2,
      "total_opportunities": 1
    },
    "value_delivery": {
      "total_composite_score": 12.47,
      "avg_composite_score": 12.47,
      "high_value_executions": 0,
      "quick_wins": 1,
      "value_categories": {
        "security": {
          "count": 1,
          "total_score": 12.47
        }
      }
    },
    "roi_analysis": {
      "estimated_savings": 0,
      "time_invested": 2,
      "roi_ratio": 0.0
    },
    "business_impact": {
      "debt_reduction_value": 0,
      "security_value": 0,
      "productivity_value": 0,
      "quality_value": 0,
      "total_estimated_value": 0
    },
    "technical_health": {
      "debt_reduction_score": 0,
      "security_posture_improvement": 0,
      "code_quality_score": 0,
      "test_coverage_improvement": 0,
      "overall_health_score": 0
    },
    "productivity_metrics": {
      "automation_hours_saved": 0,
      "manual_work_eliminated": 0,
      "developer_productivity_gain": 0.0,
      "maintenance_time_reduction": 0.0
    },
    "trend_analysis": {
      "execution_trend": "insufficient_data",
      "success_rate_trend": "insufficient_data",
      "value_delivery_trend": "insufficient_data"
    }
  },
  "roi_analysis": {
    "timestamp": "2025-08-01T05:35:51.164813",
    "investment_metrics": {
      "total_execution_time": 2,
      "system_development_time": 40,
      "maintenance_time": 2,
      "total_investment_hours": 50
    },
    "return_metrics": {
      "technical_debt_reduction": 0,
      "security_improvements": 0,
      "productivity_gains": 0,
      "quality_improvements": 0,
      "total_return_value": 0
    },
    "roi_calculations": {
      "value_per_hour": 0.0,
      "roi_percentage": -100.0,
      "payback_period_weeks": Infinity,
      "breakeven_point": "not_yet"
    }
  },
  "system_effectiveness": {
    "timestamp": "2025-08-01T05:35:51.164835",
    "discovery_effectiveness": {
      "opportunities_identified": 1,
      "opportunities_executed": 1,
      "execution_rate": 1.0,
      "avg_opportunity_value": 12.47
    },
    "execution_effectiveness": {
      "success_rate": 0.0,
      "avg_execution_time": 2,
      "failure_recovery_rate": 0,
      "quality_score": 0
    },
    "learning_effectiveness": {
      "model_adaptations": 2,
      "improvement_trend": "positive",
      "prediction_accuracy": 0.8
    },
    "overall_score": 70.0
  },
  "dashboard_generated": "/root/repo/VALUE_DASHBOARD.md"
}