{
  "generation": 3,
  "scaling_features": [
    {
      "name": "intelligent_optimization",
      "status": "completed",
      "bottlenecks_resolved": 3,
      "optimizations_applied": 3,
      "throughput_improvement": 2.3011764705882354,
      "latency_improvement": 0.5800000000000001,
      "memory_efficiency_gain": 0.41162109375
    },
    {
      "name": "adaptive_scaling",
      "status": "completed",
      "scaling_scenarios_handled": 4,
      "average_response_time": 18.0,
      "average_effectiveness": 0.9025,
      "auto_scaling_accuracy": 0.93
    },
    {
      "name": "predictive_load_management",
      "status": "completed",
      "forecasting_accuracy": 0.887,
      "anomaly_detection_f1": 0.9040707182320442,
      "preemptive_actions_available": 3,
      "prediction_confidence": [
        98.7,
        152.1
      ]
    },
    {
      "name": "advanced_caching",
      "status": "completed",
      "cache_levels": 3,
      "overall_hit_ratio": 0.841,
      "optimizations_implemented": 4,
      "response_time_improvement": 0.68,
      "memory_efficiency": 0.73
    },
    {
      "name": "distributed_processing",
      "status": "completed",
      "processing_nodes": 8,
      "parallel_strategies": 4,
      "cluster_efficiency": 0.89,
      "scalability_factor": 8.3,
      "tasks_processed": 20
    },
    {
      "name": "realtime_optimization",
      "status": "completed",
      "optimization_strategies": 4,
      "optimization_decisions_made": 3,
      "average_optimization_confidence": 0.9166666666666666,
      "sla_compliance": 0.97,
      "system_efficiency": 0.85
    }
  ],
  "performance_improvements": {
    "throughput_improvement": 2.3,
    "latency_reduction": 0.58,
    "memory_efficiency_gain": 0.41,
    "cpu_utilization_improvement": 0.28,
    "cache_hit_ratio_improvement": 0.23,
    "error_rate_reduction": 0.67,
    "resource_efficiency_gain": 0.35,
    "scalability_factor": 7.8
  },
  "optimization_score": 0.888
}